[
    {
        "type": "multiple",
        "difficulty": "easy",
        "category": "Sports",
        "question": "Which team won the 2015-16 English Premier League?",
        "correct_answer": "Leicester City",
        "incorrect_answers": [
            "Liverpool",
            "Cheslea",
            "Manchester United"
        ]
    },
    {
        "type": "multiple",
        "difficulty": "easy",
        "category": "Science: Computers",
        "question": "What does CPU stand for?",
        "correct_answer": "Central Processing Unit",
        "incorrect_answers": [
            "Central Process Unit",
            "Computer Personal Unit",
            "Central Processor Unit"
        ]
    },
    {
        "type": "multiple",
        "difficulty": "easy",
        "category": "Entertainment: Video Games",
        "question": "What year was Super Mario Bros. released?",
        "correct_answer": "1985",
        "incorrect_answers": [
            "1983",
            "1987",
            "1986"
        ]
    },
    {
        "type": "multiple",
        "difficulty": "easy",
        "category": "Entertainment: Japanese Anime &amp; Manga",
        "question": "In &quot;The Melancholy of Haruhi Suzumiya&quot; series, the SOS Brigade club leader is unknowingly treated as a(n) __ by her peers.",
        "correct_answer": "God",
        "incorrect_answers": [
            "Alien",
            "Time Traveler",
            "Esper"
        ]
    },
    {
        "type": "multiple",
        "difficulty": "easy",
        "category": "Science &amp; Nature",
        "question": "Which type of rock is created by intense heat AND pressure?",
        "correct_answer": "Metamorphic",
        "incorrect_answers": [
            "Sedimentary",
            "Igneous",
            "Diamond"
        ]
    },
    {
        "type": "multiple",
        "difficulty": "medium",
        "category": "Celebrities",
        "question": "In which situation was musician John Lennon assassinated?",
        "correct_answer": "Attempting to enter the Dakota Apartments building",
        "incorrect_answers": [
            "During an impromptu walk through Central Park",
            "Signing an autograph outside the Record Plant studio",
            "Waiting outside a music venue in Manhattan following a gig"
        ]
    },
    {
        "type": "multiple",
        "difficulty": "medium",
        "category": "Entertainment: Music",
        "question": "Who had hits in the 70s with the songs &quot;Lonely Boy&quot; and &quot;Never Let Her Slip Away&quot;?",
        "correct_answer": "Andrew Gold",
        "incorrect_answers": [
            "Elton John",
            "Leo Sayer",
            "Barry White "
        ]
    },
    {
        "type": "multiple",
        "difficulty": "medium",
        "category": "Entertainment: Cartoon &amp; Animations",
        "question": "Which of these is not a real character in the cartoon series My Little Pony: Friendship is Magic?",
        "correct_answer": "Rose Marene",
        "incorrect_answers": [
            "Pinkie Pie",
            "Maud Pie",
            "Rainbow Dash"
        ]
    },
    {
        "type": "multiple",
        "difficulty": "medium",
        "category": "Sports",
        "question": "Hockey player Wayne Gretzky was born in what Canadian province?",
        "correct_answer": "Ontario",
        "incorrect_answers": [
            "British Columbia",
            "Quebec",
            "Alberta"
        ]
    },
    {
        "type": "multiple",
        "difficulty": "medium",
        "category": "History",
        "question": "Which of these facilities was not present on the Titanic?",
        "correct_answer": "Fainting room",
        "incorrect_answers": [
            "Turkish bath",
            "Kennel",
            "Squash court"
        ]
    },
    {
        "type": "multiple",
        "difficulty": "hard",
        "category": "General Knowledge",
        "question": "What does the Latin phrase &quot;Veni, vidi, vici&quot; translate into English?",
        "correct_answer": "I came, I saw, I conquered",
        "incorrect_answers": [
            "See no evil, hear no evil, speak no evil",
            "Life, liberty, and happiness",
            "Past, present, and future"
        ]
    },
    {
        "type": "multiple",
        "difficulty": "hard",
        "category": "Entertainment: Cartoon &amp; Animations",
        "question": "In the 1968 Cartoon Show &quot;Wacky Races&quot; what was the name of cavemen duo who rode in The Boulder Mobile?",
        "correct_answer": "The Slag Brothers",
        "incorrect_answers": [
            "The Slate Brothers",
            "The Rock Brothers",
            "The Stone Brothers"
        ]
    },
    {
        "type": "multiple",
        "difficulty": "hard",
        "category": "Entertainment: Video Games",
        "question": "How many voice channels does the Nintendo Entertainment System support natively?",
        "correct_answer": "5",
        "incorrect_answers": [
            "4",
            "6",
            "3"
        ]
    },
    {
        "type": "multiple",
        "difficulty": "hard",
        "category": "History",
        "question": "Toussaint Louverture led a successful slave revolt in which country?",
        "correct_answer": "Haiti",
        "incorrect_answers": [
            "France",
            "Cuba",
            "United States"
        ]
    },
    {
        "type": "multiple",
        "difficulty": "hard",
        "category": "History",
        "question": "Bohdan Khmelnytsky was which of the following?",
        "correct_answer": "Leader of the Ukrainian Cossacks",
        "incorrect_answers": [
            "General Secretary of the Communist Party of the USSR",
            "Prince of Wallachia",
            "Grand Prince of Novgorod"
        ]
    }
]